src/reg_mem_wb.v
// =======================================
// MEM/WB: registro de señales de control de WB
// - Aquí sólo uso 1 bit (por ejemplo RF_write_enable).
//   Si tienes más, pon [N-1:0].
// =======================================
module reg_mem_wb (input clk, input reset, input wb_ctrl_in, output reg  wb_ctrl_out);
    always @(posedge clk) begin
        if (reset)
            wb_ctrl_out <= 1'b0; // en reset, NOP
        else
            wb_ctrl_out <= wb_ctrl_in;
    end
endmodule

src/reg_ex_mem.v
// =======================================
// EX/MEM: registro de señales de control de MEM
// - Ajusta [1:0] si tu bus MEM_ctrl tiene otro ancho
// =======================================
module reg_ex_mem (input clk, input reset, input [1:0] mem_ctrl_in, output reg [1:0] mem_ctrl_out);
    always @(posedge clk) begin
        if (reset)
            mem_ctrl_out <= 2'b00; // en reset, NOP
        else
            mem_ctrl_out <= mem_ctrl_in;
    end
endmodule

src/reg_id_ex.v
// =======================================
// ID/EX: registro de señales de control de EX
// - Ajusta [3:0] si tu bus EX_ctrl tiene otro ancho
// =======================================
module reg_id_ex (input clk, input reset, input [3:0] ex_ctrl_in, output reg [3:0] ex_ctrl_out);
    always @(posedge clk) begin
        if (reset)
            ex_ctrl_out <= 4'b0000; // en reset, NOP (sin control)
        else
            ex_ctrl_out <= ex_ctrl_in;
    end
endmodule

src/cu_mux_control.v
////////////////////////////////////////////////////////////////////////////////////////////////////////////////////////MUX
// =======================================
// Mux de control para la Unidad de Control
// - Si S = 0: pasan las señales originales de la CU
// - Si S = 1: se inyecta un NOP (todo ceros)
// =======================================

module cu_mux_control (input S,
    // Entradas desde el Control Unit (en etapa ID)
    input [3:0] ex_ctrl_in,
    input [1:0] mem_ctrl_in,
    input wb_ctrl_in,
    // Salidas hacia los registros de pipeline 
    output [3:0] ex_ctrl_out,
    output [1:0] mem_ctrl_out,
    output wb_ctrl_out
);
    // logica del mux
    assign ex_ctrl_out  = (S) ? 4'b0000 : ex_ctrl_in;
    assign mem_ctrl_out = (S) ? 2'b00   : mem_ctrl_in;
    assign wb_ctrl_out  = (S) ? 1'b0    : wb_ctrl_in;
endmodule

src/control_unit.v
module control_unit(
    input       [31:0]  I,
    output reg  [3:0]   ALU_OP,
    output reg  [3:0]   SOH_OP,
    output reg  [1:0]   RAM_Size,
    output reg          RAM_RW,
    output reg          RAM_Enable,
    output reg          L,
    output reg          RF_LE,
    output reg          B,
    output reg          CALL,
    output reg          JMPL
);

    always @(*) begin // combinational logic

        // defaults
        ALU_OP      = 4'b0000;
        SOH_OP      = 4'b1000;
        RAM_Size    = 2'b00;
        RAM_RW      = 1'b0;
        RAM_Enable  = 1'b0;
        L           = 1'b0;
        RF_LE       = 1'b0;
        B           = 1'b0;
        CALL        = 1'b0;
        JMPL        = 1'b0;

        // Format select (I[31:30])
        if (I[31:30] == 2'b01) begin // Format 1
            // CALL
            CALL    = 1'b1;
        end else if (I[31:30] == 2'b00) begin // Format 2
            // op2 decode (I[24:22])
            if (I[24:22] == 3'b010) begin // BRANCH
                B       = 1'b1;
                JMPL    = 1'b1;
            end else if (I[24:22] == 3'b100) begin // SETHI
                RF_LE   = 1'b1;
                SOH_OP  = 4'b0000;
            end
        end else if (I[31:30] == 2'b10) begin // Format 3; arithmetic
            // op3 decode (I[24:19])
            if (I[24:19] == 6'b010000) begin // addcc: rd <= rs1 + (rs2 or simm13), modify icc
                ALU_OP = 4'b0000;
            end else if (I[24:19] == 6'b011000) begin // addxcc: rd <= rs1 + (rs2 or simm13) + Carry, modify icc
                ALU_OP = 4'b0001;
            end else if (I[24:19] == 6'b010100) begin // subcc: rd <= rs1 - (rs2 or simm13), modify icc
                ALU_OP = 4'b0010;
            end else if (I[24:19] == 6'b011100) begin // subxcc: rd <= rs1 - (rs2 or simm13) - Carry, modify icc
                ALU_OP = 4'b0011;
            end else if (I[24:19] == 6'b010001) begin // andcc: rd <= rs1 bitwise AND (rs2 or simm13), modify icc
                ALU_OP = 4'b0100;
            end else if (I[24:19] == 6'b010010) begin // orcc: rd <= rs1 bitwise OR (rs2 or simm13), modify icc
                ALU_OP = 4'b0101;
            end else if (I[24:19] == 6'b010011) begin // xorcc: rd <= rs1 bitwise XOR (rs2 or simm13), modify icc
                ALU_OP = 4'b0110;
            end else if (I[24:19] == 6'b010111) begin // xnorcc: rd <= rs1 bitwise XNOR (rs2 or simm13), modify icc
                ALU_OP = 4'b0111;
            end else if (I[24:19] == 6'b010101) begin // andncc: rd <= rs1 bitwise AND  (NOT(rs2 or simm13)), modify icc
                ALU_OP = 4'b1000;
            end else if (I[24:19] == 6'b010110) begin // orncc: rd <= rs1 bitwise OR  (NOT(rs2 or simm13)), modify icc
                ALU_OP = 4'b1001;
            end else if (I[24:19] == 6'b100101) begin // sll: shift left logical rs1 count positions
                ALU_OP = 4'b1010;
            end else if (I[24:19] == 6'b100110) begin // srl: shift right logical rs1 count positions
                ALU_OP = 4'b1011;
            end else if (I[24:19] == 6'b100111) begin // sra: shift right arithmetic rs1 count positions
                ALU_OP = 4'b1100;
            end
            SOH_OP = I[13] ? 4'b1111 : 4'b1000;
        end else if (I[31:30] == 2'b11) begin // Format 3; load/store
            if (I[24:19] == 6'b001001) begin // lsb: load sign byte
                RAM_Size = 2'b00;
                RAM_RW   = 1'b0;
                L        = 1'b1;
                RF_LE    = 1'b1;
            end else if (I[24:19] == 6'b001010) begin // ldsh: load sign halfword
                RAM_Size = 2'b01;
                RAM_RW   = 1'b0;
                L        = 1'b1;
                RF_LE    = 1'b1;
            end else if (I[24:19] == 6'b000000) begin // ld: load word
                RAM_Size = 2'b10;
                RAM_RW   = 1'b0;
                L        = 1'b1;
                RF_LE    = 1'b1;
            end else if (I[24:19] == 6'b000001) begin // ldub: load unsigned byte
                RAM_Size = 2'b00;
                RAM_RW   = 1'b0;
                L        = 1'b1;
                RF_LE    = 1'b1;
            end else if (I[24:19] == 6'b000010) begin // lduh: load unsigned halfword
                RAM_Size = 2'b01;
                RAM_RW   = 1'b0;
                L        = 1'b1;
                RF_LE    = 1'b1;
            end else if (I[24:19] == 6'b000011) begin // ldd: load double
                RAM_Size = 2'b11;
                RAM_RW   = 1'b0;
                L        = 1'b1;
                RF_LE    = 1'b1;
            end else if (I[24:19] == 6'b000101) begin // stb: store byte
                RAM_Size   = 2'b00;
                RAM_RW     = 1'b1;
                RAM_Enable = 1'b1;
            end else if (I[24:19] == 6'b000110) begin // sth: store halfword
                RAM_Size   = 2'b01;
                RAM_RW     = 1'b1;
                RAM_Enable = 1'b1;
            end else if (I[24:19] == 6'b000100) begin // st: store word
                RAM_Size   = 2'b10;
                RAM_RW     = 1'b1;
                RAM_Enable = 1'b1;
            end else if (I[24:19] == 6'b000111) begin // std: store double
                RAM_Size   = 2'b11;
                RAM_RW     = 1'b1;
                RAM_Enable = 1'b1;
            end else if (I[24:19] == 6'b001101) begin // ldstub: atomic load-store unsigned byte ??
                RAM_Size   = 2'b00;
                RAM_RW     = 1'b1;
                RAM_Enable = 1'b1;
            end else if (I[24:19] == 6'b001111) begin // swap: swap register with memory
                RAM_Size   = 2'b10;
                RAM_RW     = 1'b1;
                RAM_Enable = 1'b1;
            end
            SOH_OP = I[13] ? 4'b1111 : 4'b1000;
        end
    end

endmodule

src/reg_if_id.v
//////////////////////////////////////////////////////////////////////////////////////////////////////////////Pipeline Reg
//Registros Pipeline

// =======================================
// IF/ID: registro de instrucción
// - Rising edge-triggered
// - Reset sincrónico
// - Sin load enable (siempre carga)
// =======================================
module reg_if_id (input clk, input reset, input [31:0] instr_in, output reg [31:0] instr_out);
    always @(posedge clk) begin
        if (reset)
            instr_out <= 32'd0;    // en reset, NOP (instrucción = 0)
        else
            instr_out <= instr_in; // siempre carga en cada ciclo
    end
endmodule

project/instruction_memory.v
`timescale 1ns/1ps
// =======================================
// Instruction Memory
// =======================================

module instruction_memory (
    input  [8:0] A,
    output reg [31:0] I
);
    reg [7:0] Memory [0:511];

    always @(*) begin
        I = {Memory[A], Memory[A+1], Memory[A+2], Memory[A+3]};
    end

    initial begin
        $readmemb("codes/testcode_sparc2.txt", Memory);
    end
endmodule

src/npc_reg.v
module npc_reg (
    input clk,
    input reset,
    input LE,
    input [31:0] D,
    output reg [31:0] Q
);
    always @(posedge clk) begin
        if (reset)
            Q <= 32'd4;
        else if (LE)
            Q <= D;
    end
endmodule

src/pc_reg.v
module pc_reg (
    input clk,
    input reset,
    input LE,
    input [31:0] D,
    output reg [31:0] Q
);
    always @(posedge clk) begin
        if (reset)
            Q <= 32'd0;
        else if (LE)
            Q <= D;
    end
endmodule

ppu.v
/////////////////////////////////////////////////////////////////////////////////////////Control path
// TOP: PPU_ControlPath
// - Conecta PC, nPC, Instruction Memory, IF/ID, Control Unit,
//   MUX de control y pipeline de señales EX/MEM/WB.
`timescale 1ns / 1ps

module ppu (
    input        clk,
    input        reset,
    input        S,               // selección del MUX de control

    // Salidas para debugging / testbench
    output [31:0] PC,
    output [31:0] nPC,
    output [31:0] instr_IF,
    output [31:0] instr_ID,
    output [3:0]  EX_ctrl,
    output [1:0]  MEM_ctrl,
    output        WB_ctrl,
    output        CALL,
    output        JMPL,
    output        B,
    output [3:0]  SOH_OP
);

    // ---------------- PC y nPC ----------------
    wire [31:0] pc_actual, npc_actual;
    wire [31:0] pc_next, npc_next, npc_plus_4;

    assign PC  = pc_actual;
    assign nPC = npc_actual;

    // nPC_next = nPC_actual + 4; PC_next = nPC_actual
    assign npc_plus_4 = npc_actual + 32'd4;
    assign pc_next    = npc_actual;
    assign npc_next   = npc_plus_4;

    // Load enable (siempre 1 por ahora)
    wire LE_PC  = 1'b1;
    wire LE_nPC = 1'b1;

    // Instancia de PC
    pc_reg PC0 (
        .clk   (clk),
        .reset (reset),
        .LE    (LE_PC),
        .D     (pc_next),
        .Q     (pc_actual)
    );

    // Instancia de nPC
    npc_reg NPC0 (
        .clk   (clk),
        .reset (reset),
        .LE    (LE_nPC),
        .D     (npc_next),
        .Q     (npc_actual)
    );

    // ---------------- Instruction Memory ----------------
    instruction_memory IMEM (
        .A(pc_actual[8:0]),   // dirección en bytes: PC[8:0]
        .I(instr_IF)
    );

    // ---------------- IF/ID: instrucción hacia la CU ----------------
    reg_if_id IF_ID (
        .clk      (clk),
        .reset    (reset),
        .instr_in (instr_IF),
        .instr_out(instr_ID)
    );

    // ---------------- Control Unit (en etapa ID) ----------------
    wire [3:0] ALU_OP;
    wire [1:0] RAM_Size;
    wire       RAM_RW, RAM_Enable, L, RF_LE;

    control_unit CU (
        .I         (instr_ID),
        .ALU_OP    (ALU_OP),
        .RAM_Size  (RAM_Size),
        .RAM_RW    (RAM_RW),
        .RAM_Enable(RAM_Enable),
        .L         (L),
        .RF_LE     (RF_LE),
        .CALL      (CALL),
        .JMPL      (JMPL),
        .B         (B),
        .SOH_OP    (SOH_OP)
    );

    // Para esta fase, mapeamos:
    //  - EX_ctrl_id  = ALU_OP (4 bits)
    //  - MEM_ctrl_id = RAM_Size (2 bits)
    //  - WB_ctrl_id  = RF_LE (1 bit)
    wire [3:0] ex_ctrl_id  = ALU_OP;
    wire [1:0] mem_ctrl_id = RAM_Size;
    wire       wb_ctrl_id  = RF_LE;

    // ---------------- Mux de control de la CU ----------------
    wire [3:0] ex_ctrl_mux;
    wire [1:0] mem_ctrl_mux;
    wire       wb_ctrl_mux;

    cu_mux_control CU_MUX (
        .S           (S),
        .ex_ctrl_in  (ex_ctrl_id),
        .mem_ctrl_in (mem_ctrl_id),
        .wb_ctrl_in  (wb_ctrl_id),
        .ex_ctrl_out (ex_ctrl_mux),
        .mem_ctrl_out(mem_ctrl_mux),
        .wb_ctrl_out (wb_ctrl_mux)
    );

    // ---------------- Registros de pipeline de control ----------------
    // ID/EX
    reg_id_ex ID_EX (
        .clk        (clk),
        .reset      (reset),
        .ex_ctrl_in (ex_ctrl_mux),
        .ex_ctrl_out(EX_ctrl)
    );

    // EX/MEM
    reg_ex_mem EX_MEM (
        .clk         (clk),
        .reset       (reset),
        .mem_ctrl_in (mem_ctrl_mux),
        .mem_ctrl_out(MEM_ctrl)
    );

    // MEM/WB
    reg_mem_wb MEM_WB (
        .clk        (clk),
        .reset      (reset),
        .wb_ctrl_in (wb_ctrl_mux),
        .wb_ctrl_out(WB_ctrl)
    );

endmodule

test/ppu_tb.v
`timescale 1ns / 1ps

module ppu_tb;

    // Testbench signals
    reg clk;
    reg reset;
    reg S;
    wire [31:0] PC, nPC, instr_IF, instr_ID;
    wire [3:0]  EX_ctrl;
    wire [1:0]  MEM_ctrl;
    wire        WB_ctrl;
    wire        CALL;
    wire        JMPL;
    wire        B;
    wire [3:0]  SOH_OP;

    // Instantiate the DUT (Device Under Test)
    ppu dut (
        .clk(clk),
        .reset(reset),
        .S(S),
        .PC(PC),
        .nPC(nPC),
        .instr_IF(instr_IF),
        .instr_ID(instr_ID),
        .EX_ctrl(EX_ctrl),
        .MEM_ctrl(MEM_ctrl),
        .WB_ctrl(WB_ctrl),
        .CALL(CALL),
        .JMPL(JMPL),
        .B(B),
        .SOH_OP(SOH_OP)
    );

    // Clock generator (10ns period)
    always #5 clk = ~clk;

    // Test sequence
    initial begin
        $dumpfile("ppu_tb.vcd");
        $dumpvars(0, ppu_tb.v);

        clk = 0;
        reset = 1;
        S = 0;

        #10;  // hold reset
        reset = 0;

        // Let the system run for a few cycles
        repeat (10) @(posedge clk);

        // Toggle S to test the MUX behavior
        S = 1;
        repeat (5) @(posedge clk);
        S = 0;

        $display("Simulation complete. PC=%d, nPC=%d", PC, nPC);
        $finish;
    end
endmodule

ppu_tb.vcd
$version Generated by VerilatedVcd $end
$timescale 1ps $end
 $scope module ppu_tb $end
  $var wire 1 5 clk $end
  $var wire 1 6 reset $end
  $var wire 1 7 S $end
  $var wire 32 # PC [31:0] $end
  $var wire 32 $ nPC [31:0] $end
  $var wire 32 8 instr_IF [31:0] $end
  $var wire 32 % instr_ID [31:0] $end
  $var wire 4 & EX_ctrl [3:0] $end
  $var wire 2 ' MEM_ctrl [1:0] $end
  $var wire 1 ( WB_ctrl $end
  $var wire 1 ) CALL $end
  $var wire 1 * JMPL $end
  $var wire 1 + B $end
  $var wire 4 , SOH_OP [3:0] $end
  $scope module dut $end
   $var wire 1 5 clk $end
   $var wire 1 6 reset $end
   $var wire 1 7 S $end
   $var wire 32 # PC [31:0] $end
   $var wire 32 $ nPC [31:0] $end
   $var wire 32 8 instr_IF [31:0] $end
   $var wire 32 % instr_ID [31:0] $end
   $var wire 4 & EX_ctrl [3:0] $end
   $var wire 2 ' MEM_ctrl [1:0] $end
   $var wire 1 ( WB_ctrl $end
   $var wire 1 ) CALL $end
   $var wire 1 * JMPL $end
   $var wire 1 + B $end
   $var wire 4 , SOH_OP [3:0] $end
   $var wire 32 # pc_actual [31:0] $end
   $var wire 32 $ npc_actual [31:0] $end
   $var wire 32 $ pc_next [31:0] $end
   $var wire 32 - npc_next [31:0] $end
   $var wire 32 - npc_plus_4 [31:0] $end
   $var wire 1 < LE_PC $end
   $var wire 1 < LE_nPC $end
   $var wire 4 . ALU_OP [3:0] $end
   $var wire 2 / RAM_Size [1:0] $end
   $var wire 1 0 RAM_RW $end
   $var wire 1 1 RAM_Enable $end
   $var wire 1 2 L $end
   $var wire 1 3 RF_LE $end
   $var wire 4 . ex_ctrl_id [3:0] $end
   $var wire 2 / mem_ctrl_id [1:0] $end
   $var wire 1 3 wb_ctrl_id $end
   $var wire 4 9 ex_ctrl_mux [3:0] $end
   $var wire 2 : mem_ctrl_mux [1:0] $end
   $var wire 1 ; wb_ctrl_mux $end
   $scope module CU $end
    $var wire 32 % I [31:0] $end
    $var wire 4 . ALU_OP [3:0] $end
    $var wire 4 , SOH_OP [3:0] $end
    $var wire 2 / RAM_Size [1:0] $end
    $var wire 1 0 RAM_RW $end
    $var wire 1 1 RAM_Enable $end
    $var wire 1 2 L $end
    $var wire 1 3 RF_LE $end
    $var wire 1 + B $end
    $var wire 1 ) CALL $end
    $var wire 1 * JMPL $end
   $upscope $end
   $scope module CU_MUX $end
    $var wire 1 7 S $end
    $var wire 4 . ex_ctrl_in [3:0] $end
    $var wire 2 / mem_ctrl_in [1:0] $end
    $var wire 1 3 wb_ctrl_in $end
    $var wire 4 9 ex_ctrl_out [3:0] $end
    $var wire 2 : mem_ctrl_out [1:0] $end
    $var wire 1 ; wb_ctrl_out $end
   $upscope $end
   $scope module EX_MEM $end
    $var wire 1 5 clk $end
    $var wire 1 6 reset $end
    $var wire 2 : mem_ctrl_in [1:0] $end
    $var wire 2 ' mem_ctrl_out [1:0] $end
   $upscope $end
   $scope module ID_EX $end
    $var wire 1 5 clk $end
    $var wire 1 6 reset $end
    $var wire 4 9 ex_ctrl_in [3:0] $end
    $var wire 4 & ex_ctrl_out [3:0] $end
   $upscope $end
   $scope module IF_ID $end
    $var wire 1 5 clk $end
    $var wire 1 6 reset $end
    $var wire 32 8 instr_in [31:0] $end
    $var wire 32 % instr_out [31:0] $end
   $upscope $end
   $scope module IMEM $end
    $var wire 9 4 A [8:0] $end
    $var wire 32 8 I [31:0] $end
   $upscope $end
   $scope module MEM_WB $end
    $var wire 1 5 clk $end
    $var wire 1 6 reset $end
    $var wire 1 ; wb_ctrl_in $end
    $var wire 1 ( wb_ctrl_out $end
   $upscope $end
   $scope module NPC0 $end
    $var wire 1 5 clk $end
    $var wire 1 6 reset $end
    $var wire 1 < LE $end
    $var wire 32 - D [31:0] $end
    $var wire 32 $ Q [31:0] $end
   $upscope $end
   $scope module PC0 $end
    $var wire 1 5 clk $end
    $var wire 1 6 reset $end
    $var wire 1 < LE $end
    $var wire 32 $ D [31:0] $end
    $var wire 32 # Q [31:0] $end
   $upscope $end
  $upscope $end
 $upscope $end
$enddefinitions $end


#0
b00000000000000000000000000000000 #
b00000000000000000000000000000000 $
b00000000000000000000000000000000 %
b0000 &
b00 '
0(
0)
0*
0+
b1000 ,
b00000000000000000000000000000100 -
b0000 .
b00 /
00
01
02
03
b000000000 4
05
16
07
b10001010000000000000000000000000 8
b0000 9
b00 :
0;
1<
#5000
b00000000000000000000000000000100 $
b00000000000000000000000000001000 -
15
#10000
05
06
#15000
b00000000000000000000000000000100 #
b00000000000000000000000000001000 $
b10001010000000000000000000000000 %
b00000000000000000000000000001100 -
b000000100 4
15
b10000110101000001110000000000001 8
#20000
05
#25000
b00000000000000000000000000001000 #
b00000000000000000000000000001100 $
b10000110101000001110000000000001 %
b1111 ,
b00000000000000000000000000010000 -
b0010 .
b000001000 4
15
b11000100000010000000000000000001 8
b0010 9
#30000
05
#35000
b00000000000000000000000000001100 #
b00000000000000000000000000010000 $
b11000100000010000000000000000001 %
b0010 &
b1000 ,
b00000000000000000000000000010100 -
b0000 .
12
13
b000001100 4
15
b11001010001010000110000000000001 8
b0000 9
1;
#40000
05
#45000
b00000000000000000000000000010000 #
b00000000000000000000000000010100 $
b11001010001010000110000000000001 %
b0000 &
1(
b1111 ,
b00000000000000000000000000011000 -
10
11
02
03
b000010000 4
15
b00010010101111111111111111111110 8
0;
#50000
05
#55000
b00000000000000000000000000010100 #
b00000000000000000000000000011000 $
b00010010101111111111111111111110 %
0(
1*
1+
b1000 ,
b00000000000000000000000000011100 -
00
01
b000010100 4
15
b00001011000011110000111100000110 8
#60000
05
#65000
b00000000000000000000000000011000 #
b00000000000000000000000000011100 $
b00001011000011110000111100000110 %
0*
0+
b0000 ,
b00000000000000000000000000100000 -
13
b000011000 4
15
b01000000000000000000000000000100 8
1;
#70000
05
#75000
b00000000000000000000000000011100 #
b00000000000000000000000000100000 $
b01000000000000000000000000000100 %
1(
1)
b1000 ,
b00000000000000000000000000100100 -
03
b000011100 4
15
b10000001110000000000000000001111 8
0;
#80000
05
#85000
b00000000000000000000000000100000 #
b00000000000000000000000000100100 $
b10000001110000000000000000001111 %
0(
0)
b00000000000000000000000000101000 -
b000100000 4
15
b10001010000000000000000000000000 8
#90000
05
#95000
b00000000000000000000000000100100 #
b00000000000000000000000000101000 $
b10001010000000000000000000000000 %
b00000000000000000000000000101100 -
b000100100 4
15
b10000110101000001110000000000001 8
#100000
05
#105000
b00000000000000000000000000101000 #
b00000000000000000000000000101100 $
b10000110101000001110000000000001 %
b1111 ,
b00000000000000000000000000110000 -
b0010 .
b000101000 4
15
17
b11000100000010000000000000000001 8
#110000
05
#115000
b00000000000000000000000000101100 #
b00000000000000000000000000110000 $
b11000100000010000000000000000001 %
b1000 ,
b00000000000000000000000000110100 -
b0000 .
12
13
b000101100 4
15
b00000000000000000000000000000000 8
#120000
05
#125000
b00000000000000000000000000110000 #
b00000000000000000000000000110100 $
b00000000000000000000000000000000 %
b00000000000000000000000000111000 -
02
03
b000110000 4
15
b00010010101111111111111111111110 8
#130000
05
#135000
b00000000000000000000000000110100 #
b00000000000000000000000000111000 $
b00010010101111111111111111111110 %
1*
1+
b00000000000000000000000000111100 -
b000110100 4
15
b00000000000000000000000000000000 8
#140000
05
#145000
b00000000000000000000000000111000 #
b00000000000000000000000000111100 $
b00000000000000000000000000000000 %
0*
0+
b00000000000000000000000001000000 -
b000111000 4
15
#150000
05
#155000
b00000000000000000000000000111100 #
b00000000000000000000000001000000 $
b00000000000000000000000001000100 -
b000111100 4
15
07
