fase_2/src/MEM_WB_reg.v
// =======================================
// MEM/WB: registro de señales de control de WB
// =======================================
module MEM_WB_reg (
    input              clk, 
    input              reset, 
    input       [31:0] mem_ctrl_in, 
    output reg  [31:0] wb_ctrl_out
);
    always @(posedge clk) begin
        if (reset)
            wb_ctrl_out <= 32'b0; // en reset, NOP
        else
            wb_ctrl_out <= mem_ctrl_in;
    end
endmodule

fase_2/src/EX_MEM_reg.v
// =======================================
// EX/MEM: registro de señales de control de MEM
// =======================================
module EX_MEM_reg (
    input              clk, 
    input              reset, 
    input       [31:0] ex_ctrl_in, 
    output reg  [31:0] mem_ctrl_out
);

    always @(posedge clk) begin
        if (reset)
            mem_ctrl_out <= 32'b0; // en reset, NOP
        else
            mem_ctrl_out <= ex_ctrl_in;
    end
endmodule

fase_2/src/ID_EX_reg.v
// =======================================
// ID/EX: registro de señales de control de EX
// =======================================
module ID_EX_reg (
    input clk,
    input reset,
    input [31:0] id_ctrl_in,
    output reg [31:0] ex_ctrl_out
);

    always @(posedge clk) begin
        if (reset)
            ex_ctrl_out <= 32'b0; // en reset, NOP
        else
            ex_ctrl_out <= id_ctrl_in;
    end
endmodule

fase_2/src/CU_Mux_Control.v
////////////////////////////////////////////////////////////////////////////////////////////////////////////////////////MUX
// =======================================
// Mux de control para la Unidad de Control
// - Si S = 0: pasan las señales originales de la CU
// - Si S = 1: se inyecta un NOP (todo ceros)
// =======================================

module CU_Mux_Control (
    // Entradas desde el Control Unit (en etapa ID)
    input S,
    input [31:0] id_ctrl_in,
    // Salidas hacia los registros de pipeline
    output [31:0] id_ctrl_out
);
    // logica del mux
    assign id_ctrl_out = (S) ? 32'b0 : id_ctrl_in;
endmodule

fase_2/src/control_unit.v
`timescale 1ns / 1ps

module control_unit(
    input  [31:0] I,

    output reg [31:0] control_signals
);
    // Initialize control signals
    reg [3:0]  ALU_OP;
    reg [3:0]  SOH_OP;
    reg [1:0]  RAM_Size;
    reg        RAM_RW;
    reg        RAM_Enable;
    reg        L;
    reg        RF_LE;
    reg        call;
    reg        jmpl;
    reg        B;

    // Combinational control logic
    always @(*) begin
        // Default values
        ALU_OP     = 4'b0000;
        SOH_OP     = 4'b0000;
        RAM_Size   = 2'b00;
        RAM_RW     = 1'b0;
        RAM_Enable = 1'b0;
        L          = 1'b0;
        RF_LE      = 1'b0;
        call       = 1'b0;
        jmpl       = 1'b0;
        B          = 1'b0;
        control_signals = 32'b0;

        case (I[31:30])
            2'b01: begin
                // Format 1: CALL (placeholder)
            end

            2'b00: begin // Format 2
                case (I[24:22]) // op2 field
                    3'b010: begin // BRANCH
                        // Placeholder for branch control
                    end
                    3'b100: begin // SETHI

                    end
                endcase
            end

            2'b10: begin // Format 3: Arithmetic/Logic
                case (I[24:19]) // op3
                    // Arithmetic
                    6'b010000: ALU_OP = 4'b0000; // addcc
                    6'b011000: ALU_OP = 4'b0001; // addxcc
                    6'b010100: ALU_OP = 4'b0010; // subcc
                    6'b011100: ALU_OP = 4'b0011; // subxcc

                    // Logical
                    6'b010001: ALU_OP = 4'b0100; // andcc
                    6'b010010: ALU_OP = 4'b0101; // orcc
                    6'b010011: ALU_OP = 4'b0110; // xorcc
                    6'b010111: ALU_OP = 4'b0111; // xnorcc
                    6'b010101: ALU_OP = 4'b1000; // andncc
                    6'b010110: ALU_OP = 4'b1001; // orncc

                    // Shifts
                    6'b100101: ALU_OP = 4'b1010; // sll
                    6'b100110: ALU_OP = 4'b1011; // srl
                    6'b100111: ALU_OP = 4'b1100; // sra
                endcase
            end

            2'b11: begin // Format 3: Load/Store
                case (I[24:19]) // op3
                    // Loads
                    6'b001001: begin // lsb
                        RAM_Size = 2'b00;
                        RAM_RW   = 1'b0;
                        RAM_Enable = 1'b1;
                        L        = 1'b1;
                        RF_LE    = 1'b1;
                    end
                    6'b001010: begin // ldsh
                        RAM_Size = 2'b01;
                        RAM_RW   = 1'b0;
                        RAM_Enable = 1'b1;
                        L        = 1'b1;
                        RF_LE    = 1'b1;
                    end
                    6'b000000: begin // ld
                        RAM_Size = 2'b10;
                        RAM_RW   = 1'b0;
                        RAM_Enable = 1'b1;
                        L        = 1'b1;
                        RF_LE    = 1'b1;
                    end
                    6'b000001: begin // ldub
                        RAM_Size = 2'b00;
                        RAM_RW   = 1'b0;
                        RAM_Enable = 1'b1;
                        L        = 1'b1;
                        RF_LE    = 1'b1;
                    end
                    6'b000010: begin // lduh
                        RAM_Size = 2'b01;
                        RAM_RW   = 1'b0;
                        RAM_Enable = 1'b1;
                        L        = 1'b1;
                        RF_LE    = 1'b1;
                    end
                    6'b000011: begin // ldd
                        RAM_Size = 2'b11;
                        RAM_RW   = 1'b0;
                        RAM_Enable = 1'b1;
                        L        = 1'b1;
                        RF_LE    = 1'b1;
                    end

                    // Stores
                    6'b000101: begin // stb
                        RAM_Size   = 2'b00;
                        RAM_RW     = 1'b1;
                        RAM_Enable = 1'b1;
                    end
                    6'b000110: begin // sth
                        RAM_Size   = 2'b01;
                        RAM_RW     = 1'b1;
                        RAM_Enable = 1'b1;
                    end
                    6'b000100: begin // st
                        RAM_Size   = 2'b10;
                        RAM_RW     = 1'b1;
                        RAM_Enable = 1'b1;
                    end
                    6'b000111: begin // std
                        RAM_Size   = 2'b11;
                        RAM_RW     = 1'b1;
                        RAM_Enable = 1'b1;
                    end
                    6'b001101: begin // ldstub
                        RAM_Size   = 2'b00;
                        RAM_RW     = 1'b1;
                        RAM_Enable = 1'b1;
                    end
                    6'b001111: begin // swap
                        RAM_Size   = 2'b10;
                        RAM_RW     = 1'b1;
                        RAM_Enable = 1'b1;
                    end
                endcase
            end

            default: begin
                // no-op
            end
        endcase

       control_signals = {15'b0, ALU_OP, SOH_OP, RAM_Size, RAM_RW, RAM_Enable, L, RF_LE, call, jmpl, B}; 
    end

endmodule

fase_2/src/IF_ID_reg.v
//////////////////////////////////////////////////////////////////////////////////////////////////////////////Pipeline Reg
//Registros Pipeline

// =======================================
// IF/ID: registro de instrucción
// - Rising edge-triggered
// - Reset sincrónico
// - Sin load enable (siempre carga)
// =======================================
module IF_ID_reg (
    input clk, 
    input reset, 
    input [31:0] instr_in, 
    output reg [31:0] instr_out
);
    always @(posedge clk) begin
        if (reset)
            instr_out <= 32'd0;    // en reset, NOP (instrucción = 0)
        else
            instr_out <= instr_in; // siempre carga en cada ciclo
    end
endmodule

fase_2/src/instruction_memory.v
`timescale 1ns/1ps
// =======================================
// Instruction Memory
// - 512 bytes de memoria (128 instrucciones de 32 bits)
// - Dirección de 9 bits (byte addressable)
// - Salida de 32 bits (instrucción)
// =======================================
module instruction_memory (
    input [8:0] A,
    output reg [31:0] I
);
    reg [7:0] Memory [0:511];

    always @(*) begin
        I = {Memory[A], Memory[A+1], Memory[A+2], Memory[A+3]};
    end

    initial begin
        $readmemb("precharge.txt", Memory);
    end
endmodule

fase_2/src/NPC_reg.v
// =======================================
// NPC_reg: registro del Next Program Counter (NPC)
// - Rising edge-triggered
// - Reset sincrónico (inicializa a 4)
// - Load Enable (LE)
// =======================================
module NPC_reg (
    input clk,
    input reset,
    input LE,
    input [8:0] D,
    output reg [8:0] Q
);
    always @(posedge clk) begin
        if (reset)
            Q <= 8'd4;
        else if (LE)
            Q <= D;
    end
endmodule

fase_2/src/PC_reg.v
// =======================================
// PC_reg: registro del Program Counter (PC)
// - Rising edge-triggered
// - Reset sincrónico (inicializa a 0)
// - Load Enable (LE)
// =======================================
module PC_reg (
    input clk,
    input reset,
    input LE,
    input [8:0] D,
    output reg [8:0] Q
);
    always @(posedge clk) begin
        if (reset)
            Q <= 8'd0;
        else if (LE)
            Q <= D;
    end
endmodule

fase_2/src/PPU_ControlPath.v
/////////////////////////////////////////////////////////////////////////////////////////Control path
// TOP: PPU_ControlPath
// - Conecta PC, nPC, Instruction Memory, IF/ID, Control Unit,
//   MUX de control y pipeline de señales EX/MEM/WB.

module PPU_ControlPath (
    input        clk,
    input        reset,
    input        S,             // selección del MUX de control

    // Salidas para debugging / testbench
    output [8:0] PC,
    output [8:0] nPC,
    output [31:0] instr_IF,
    output [31:0] instr_ID,
    output [31:0] EX_ctrl,
    output [31:0] MEM_ctrl,
    output [31:0] WB_ctrl,
    output [31:0] control_signals

);

    // ---------------- PC y nPC ----------------
    wire [8:0] pc_actual, npc_actual;
    wire [8:0] pc_next, npc_next, npc_plus_4;

    assign PC  = pc_actual;
    assign nPC = npc_actual;

    // nPC_next = nPC_actual + 4; PC_next = nPC_actual
    assign npc_plus_4 = npc_actual + 32'd4;
    assign pc_next    = npc_actual;
    assign npc_next   = npc_plus_4;

    // Load enable (siempre 1 por ahora)
    wire LE_PC  = 1'b1;
    wire LE_nPC = 1'b1;

    // Instancia de PC
    PC_reg PC0 (
        .clk   (clk),
        .reset (reset),
        .LE    (LE_PC),
        .D     (pc_next),
        .Q     (pc_actual)
    );

    // Instancia de nPC
    NPC_reg NPC0 (
        .clk   (clk),
        .reset (reset),
        .LE    (LE_nPC),
        .D     (npc_next),
        .Q     (npc_actual)
    );

    // ---------------- Instruction Memory ----------------
    instruction_memory IMEM (
        .A(pc_actual[8:0]),   // dirección en bytes: PC[8:0]
        .I(instr_IF)
    );

    // ---------------- IF/ID: instrucción hacia la CU ----------------
    IF_ID_reg IF_ID (
        .clk      (clk),
        .reset    (reset),
        .instr_in (instr_IF),
        .instr_out(instr_ID)
    );

    // ---------------- Control Unit (en etapa ID) ----------------
    control_unit CU (
        .I         (instr_ID),
        .control_signals(control_signals)
    );

    // ---------------- Mux de control de la CU ----------------
    wire [31:0] id_ctrl_mux;

    CU_Mux_Control CU_MUX (
        .S           (S),
        .id_ctrl_in  (control_signals),
        .id_ctrl_out (id_ctrl_mux)
    );

    // ---------------- Registros de pipeline de control ----------------
    // ID/EX
    ID_EX_reg ID_EX (
        .clk        (clk),
        .reset      (reset),
        .id_ctrl_in (id_ctrl_mux),
        .ex_ctrl_out(EX_ctrl)
    );

    // EX/MEM
    EX_MEM_reg EX_MEM (
        .clk         (clk),
        .reset       (reset),
        .ex_ctrl_in (EX_ctrl),
        .mem_ctrl_out(MEM_ctrl)
    );

    // MEM/WB
    MEM_WB_reg MEM_WB (
        .clk        (clk),
        .reset      (reset),
        .mem_ctrl_in (MEM_ctrl),
        .wb_ctrl_out(WB_ctrl)
    );

endmodule

fase_2/src/PPU_ControlPath_tb.v
`timescale 1ns / 1ps

module PPU_ControlPath_tb;

    // Testbench signals
    reg clk;
    reg reset;
    reg S;
    reg [31:0] control_signals;
    wire [31:0]instr_IF, instr_ID, EX_ctrl, MEM_ctrl, WB_ctrl;
    wire [8:0] PC, nPC;

    // Instantiate the DUT (Device Under Test)
    PPU_ControlPath dut (
        .clk(clk),
        .reset(reset),
        .S(S),
        .PC(PC),
        .nPC(nPC),
        .instr_IF(instr_IF),
        .instr_ID(instr_ID),
        .EX_ctrl(EX_ctrl),
        .MEM_ctrl(MEM_ctrl),
        .WB_ctrl(WB_ctrl)
    );

    // Clock generator: toggles every 2ns → period = 4ns
    initial begin
        clk = 0;
        forever #2 clk = ~clk;
    end

    // Test sequence according to spec
    initial begin
        $dumpfile("PPU_ControlPath_tb.vcd");
        $dumpvars(0, PPU_ControlPath_tb);

        // Inicialización
        reset = 1;
        S = 0;

        // Reset va a 0 en t=3 ns
        #3 reset = 0;

        // S cambia a 1 en t=40 ns
        #40 S = 1;

        // Finaliza en t=48 ns
        #48;
        $display("=== SIMULACION FINALIZADA ===");
        $finish;
    end

    // --- Instrucción decodificada (opcional) ---
    reg [7:0] opcode;
    reg [5:0]  opcode3;
    reg [31:0] instr_word;

    // Cada flanco positivo del reloj, imprimir estado
    always @(posedge clk) begin
        instr_word = instr_ID;
        opcode = instr_word[31:30];
        opcode3 = instr_word[24:19];
        $display("------------------------------------------------");
        $write("t=%0t ns | ", $time);
        case (opcode)
            2'b00: $write("Instr=SETHI or BRANCH ");   // Format 2
            2'b01: $write("Instr=CALL ");              // Format 1

            2'b10: begin // Format 3 – Arithmetic, Logic, Shift, Save/Restore, Trap, etc.
                case (opcode3)
                    // Basic Arithmetic Instructions
                    6'b000000: $write("Instr=ADD ");
                    6'b010000: $write("Instr=ADDCC ");
                    6'b001000: $write("Instr=ADDX ");
                    6'b011000: $write("Instr=ADDXCC ");
                    6'b000100: $write("Instr=SUB ");
                    6'b010100: $write("Instr=SUBCC ");
                    6'b001100: $write("Instr=SUBX ");
                    6'b011100: $write("Instr=SUBXCC ");
                    // Tagged Arithmetic Instructions
                    6'b100000: $write("Instr=TADDCC ");
                    6'b100010: $write("Instr=TADDCCTV ");
                    6'b100001: $write("Instr=TSUBCC ");
                    6'b100011: $write("Instr=TSUBCCTV ");
                    // Other Arithmetic Instructions
                    6'b100101: $write("Instr=MULSCC ");
                    6'b001010: $write("Instr=UMUL ");
                    6'b011010: $write("Instr=UMULCC ");
                    6'b001001: $write("Instr=SMUL ");
                    6'b011001: $write("Instr=SMULCC ");
                    6'b001110: $write("Instr=UDIV ");
                    6'b011110: $write("Instr=UDIVCC ");
                    6'b001111: $write("Instr=SDIV ");
                    6'b011111: $write("Instr=SDIVCC ");

                    // Logical Instructions
                    6'b000001: $write("Instr=AND ");
                    6'b010001: $write("Instr=ANDCC ");
                    6'b000101: $write("Instr=ANDN ");
                    6'b010101: $write("Instr=ANDNCC ");
                    6'b000010: $write("Instr=OR ");
                    6'b010010: $write("Instr=ORCC ");
                    6'b000110: $write("Instr=ORN ");
                    6'b010110: $write("Instr=ORNCC ");
                    6'b000011: $write("Instr=XOR ");
                    6'b010011: $write("Instr=XORCC ");
                    6'b000111: $write("Instr=XNOR ");
                    6'b010111: $write("Instr=XNORCC ");

                    // Shift Instructions
                    6'b100101: $write("Instr=SLL ");
                    6'b100110: $write("Instr=SRL ");
                    6'b100111: $write("Instr=SRA ");

                    // Save and Restore Instruction Format
                    6'b111100: $write("Instr=SAVE ");
                    6'b111101: $write("Instr=RESTORE ");

                    // jumpl Instruction
                    6'b111000: $write("Instr=JMPL ");

                    // Trap on Integer Condition Codes
                    6'b111010: $write("Instr=TRAP "); // These expand even more, slide 54 of CA SPARC Architecture
                    
                    // Return from Trap Instruction - RETT
                    6'b111001: $write("Instr=RETT ");

                    // Read State Register Instructions
                    6'b101001: $write("Instr=RDPSR ");
                    6'b101010: $write("Instr=RDWIM ");
                    6'b101011: $write("Instr=RDTBR ");

                    // Write State Register Instructions
                    6'b110001: $write("Instr=WRPSR ");
                    6'b110010: $write("Instr=WRWIM ");
                    6'b110011: $write("Instr=WRTBR ");

                    default:   $write("Instr=UNKNOWN (op3=%b)", opcode3);
                endcase
            end

            2'b11: begin
                case (opcode3)
                    6'b001001: $write("Instr=LSB ");
                    6'b001010: $write("Instr=LDSH ");
                    6'b000000: $write("Instr=LD ");
                    6'b000001: $write("Instr=LDUB ");
                    6'b000010: $write("Instr=LDUH ");
                    6'b000011: $write("Instr=LDD ");
                    6'b000101: $write("Instr=STB ");
                    6'b000110: $write("Instr=STH ");
                    6'b000100: $write("Instr=ST ");
                    6'b000111: $write("Instr=STD ");
                    6'b001101: $write("Instr=LDSTUB ");
                    6'b001111: $write("Instr=SWAP ");
                    default:   $write("Instr=LOAD/STORE OTHER ");
                endcase
            end

            default: $write("Instr=UNKNOWN OP ");
        endcase
        // Mostrar NPC y PC
        $display("| PC=%0d | nPC=%0d", PC, nPC);

        // Mostrar señales de control
        $display("Control Signals:");
        $display("ALU_OP=%b", control_signals[16:13]);
        $display("SOH_OP=%b", control_signals[12:9]);
        $display("RAM_Size=%b", control_signals[8:7]);
        $display("RAM_RW=%b", control_signals[6]);
        $display("RAM_Enable=%b", control_signals[5]);
        $display("L=%b", control_signals[4]);
        $display("RF_LE=%b", control_signals[3]);
        $display("call=%b", control_signals[2]);
        $display("jmpl=%b", control_signals[1]);
        $display("B=%b", control_signals[0]);

        // Mostrar señales de control de la etapa EX, MEM y WB
        $display("EX_ctrl=%b", EX_ctrl);
        $display("MEM_ctrl=%b", MEM_ctrl);
        $display("WB_ctrl=%b", WB_ctrl);

    end

endmodule

fase_2/src/PPU_ControlPath_tb.vcd
$date
	Sat Nov 08 17:52:26 2025
$end
$version
	Icarus Verilog
$end
$timescale
	1ps
$end
$scope module PPU_ControlPath_tb $end
$var wire 9 ! nPC [8:0] $end
$var wire 32 " instr_IF [31:0] $end
$var wire 32 # instr_ID [31:0] $end
$var wire 32 $ WB_ctrl [31:0] $end
$var wire 9 % PC [8:0] $end
$var wire 32 & MEM_ctrl [31:0] $end
$var wire 32 ' EX_ctrl [31:0] $end
$var reg 1 ( S $end
$var reg 1 ) clk $end
$var reg 32 * control_signals [31:0] $end
$var reg 32 + instr_word [31:0] $end
$var reg 8 , opcode [7:0] $end
$var reg 6 - opcode3 [5:0] $end
$var reg 1 . reset $end
$scope module dut $end
$var wire 1 / LE_PC $end
$var wire 1 0 LE_nPC $end
$var wire 9 1 PC [8:0] $end
$var wire 1 ( S $end
$var wire 1 ) clk $end
$var wire 9 2 nPC [8:0] $end
$var wire 9 3 npc_next [8:0] $end
$var wire 9 4 pc_next [8:0] $end
$var wire 1 . reset $end
$var wire 9 5 pc_actual [8:0] $end
$var wire 9 6 npc_plus_4 [8:0] $end
$var wire 9 7 npc_actual [8:0] $end
$var wire 32 8 instr_IF [31:0] $end
$var wire 32 9 instr_ID [31:0] $end
$var wire 32 : id_ctrl_mux [31:0] $end
$var wire 32 ; control_signals [31:0] $end
$var wire 32 < WB_ctrl [31:0] $end
$var wire 32 = MEM_ctrl [31:0] $end
$var wire 32 > EX_ctrl [31:0] $end
$scope module CU $end
$var wire 32 ? I [31:0] $end
$var reg 4 @ ALU_OP [3:0] $end
$var reg 1 A B $end
$var reg 1 B L $end
$var reg 1 C RAM_Enable $end
$var reg 1 D RAM_RW $end
$var reg 2 E RAM_Size [1:0] $end
$var reg 1 F RF_LE $end
$var reg 4 G SOH_OP [3:0] $end
$var reg 1 H call $end
$var reg 32 I control_signals [31:0] $end
$var reg 1 J jmpl $end
$upscope $end
$scope module CU_MUX $end
$var wire 1 ( S $end
$var wire 32 K id_ctrl_in [31:0] $end
$var wire 32 L id_ctrl_out [31:0] $end
$upscope $end
$scope module EX_MEM $end
$var wire 1 ) clk $end
$var wire 1 . reset $end
$var wire 32 M ex_ctrl_in [31:0] $end
$var reg 32 N mem_ctrl_out [31:0] $end
$upscope $end
$scope module ID_EX $end
$var wire 1 ) clk $end
$var wire 32 O id_ctrl_in [31:0] $end
$var wire 1 . reset $end
$var reg 32 P ex_ctrl_out [31:0] $end
$upscope $end
$scope module IF_ID $end
$var wire 1 ) clk $end
$var wire 1 . reset $end
$var wire 32 Q instr_in [31:0] $end
$var reg 32 R instr_out [31:0] $end
$upscope $end
$scope module IMEM $end
$var wire 9 S A [8:0] $end
$var reg 32 T I [31:0] $end
$upscope $end
$scope module MEM_WB $end
$var wire 1 ) clk $end
$var wire 32 U mem_ctrl_in [31:0] $end
$var wire 1 . reset $end
$var reg 32 V wb_ctrl_out [31:0] $end
$upscope $end
$scope module NPC0 $end
$var wire 9 W D [8:0] $end
$var wire 1 0 LE $end
$var wire 1 ) clk $end
$var wire 1 . reset $end
$var reg 9 X Q [8:0] $end
$upscope $end
$scope module PC0 $end
$var wire 9 Y D [8:0] $end
$var wire 1 / LE $end
$var wire 1 ) clk $end
$var wire 1 . reset $end
$var reg 9 Z Q [8:0] $end
$upscope $end
$upscope $end
$upscope $end
$enddefinitions $end
$comment Show the parameter values. $end
$dumpall
$end
#0
$dumpvars
bx Z
bx Y
bx X
bx W
bx V
bx U
bx T
bx S
bx R
bx Q
bx P
bx O
bx N
bx M
bx L
bx K
xJ
bx I
xH
bx G
xF
bx E
xD
xC
xB
xA
bx @
bx ?
bx >
bx =
bx <
bx ;
bx :
bx 9
bx 8
bx 7
bx 6
bx 5
bx 4
bx 3
bx 2
bx 1
10
1/
1.
bx -
bx ,
bx +
bx *
0)
0(
bx '
bx &
bx %
bx $
bx #
bx "
bx !
$end
#2000
b0 :
b0 L
b0 O
b10001010000000000000000000000000 "
b10001010000000000000000000000000 8
b10001010000000000000000000000000 Q
b10001010000000000000000000000000 T
b1000 3
b1000 W
b1000 6
b0 ;
b0 I
b0 K
0A
0J
0H
0F
0B
0C
0D
b0 E
b0 G
b0 @
b0 %
b0 1
b0 5
b0 S
b0 Z
b100 4
b100 Y
b100 !
b100 2
b100 7
b100 X
b0 #
b0 9
b0 ?
b0 R
b0 '
b0 >
b0 M
b0 P
b0 &
b0 =
b0 N
b0 U
b0 $
b0 <
b0 V
b0xx ,
1)
#3000
0.
#4000
0)
#6000
b1100 3
b1100 W
b1100 6
b10000110101000001110000000000001 "
b10000110101000001110000000000001 8
b10000110101000001110000000000001 Q
b10000110101000001110000000000001 T
b10001010000000000000000000000000 #
b10001010000000000000000000000000 9
b10001010000000000000000000000000 ?
b10001010000000000000000000000000 R
b1000 4
b1000 Y
b1000 !
b1000 2
b1000 7
b1000 X
b100 %
b100 1
b100 5
b100 S
b100 Z
b0 -
b0 ,
b0 +
1)
#8000
0)
#10000
b100000000000000 :
b100000000000000 L
b100000000000000 O
b11000100000010000000000000000001 "
b11000100000010000000000000000001 8
b11000100000010000000000000000001 Q
b11000100000010000000000000000001 T
b10000 3
b10000 W
b10000 6
b100000000000000 ;
b100000000000000 I
b100000000000000 K
b10 @
b1000 %
b1000 1
b1000 5
b1000 S
b1000 Z
b1100 4
b1100 Y
b1100 !
b1100 2
b1100 7
b1100 X
b10000110101000001110000000000001 #
b10000110101000001110000000000001 9
b10000110101000001110000000000001 ?
b10000110101000001110000000000001 R
b10 ,
b10001010000000000000000000000000 +
1)
#12000
0)
#14000
b111000 :
b111000 L
b111000 O
1F
1B
1C
b111000 ;
b111000 I
b111000 K
b0 @
b10100 3
b10100 W
b10100 6
b11001010001010000110000000000001 "
b11001010001010000110000000000001 8
b11001010001010000110000000000001 Q
b11001010001010000110000000000001 T
b100000000000000 '
b100000000000000 >
b100000000000000 M
b100000000000000 P
b11000100000010000000000000000001 #
b11000100000010000000000000000001 9
b11000100000010000000000000000001 ?
b11000100000010000000000000000001 R
b10000 4
b10000 Y
b10000 !
b10000 2
b10000 7
b10000 X
b1100 %
b1100 1
b1100 5
b1100 S
b1100 Z
b10100 -
b10000110101000001110000000000001 +
1)
#16000
0)
#18000
b1100000 :
b1100000 L
b1100000 O
b10010101111111111111111111110 "
b10010101111111111111111111110 8
b10010101111111111111111111110 Q
b10010101111111111111111111110 T
b11000 3
b11000 W
b11000 6
1D
b1100000 ;
b1100000 I
b1100000 K
0F
0B
1C
b10000 %
b10000 1
b10000 5
b10000 S
b10000 Z
b10100 4
b10100 Y
b10100 !
b10100 2
b10100 7
b10100 X
b11001010001010000110000000000001 #
b11001010001010000110000000000001 9
b11001010001010000110000000000001 ?
b11001010001010000110000000000001 R
b111000 '
b111000 >
b111000 M
b111000 P
b100000000000000 &
b100000000000000 =
b100000000000000 N
b100000000000000 U
b1 -
b11 ,
b11000100000010000000000000000001 +
1)
#20000
0)
#22000
b0 :
b0 L
b0 O
b0 ;
b0 I
b0 K
0C
0D
b11100 3
b11100 W
b11100 6
b1011000011110000111100000110 "
b1011000011110000111100000110 8
b1011000011110000111100000110 Q
b1011000011110000111100000110 T
b100000000000000 $
b100000000000000 <
b100000000000000 V
b111000 &
b111000 =
b111000 N
b111000 U
b1100000 '
b1100000 >
b1100000 M
b1100000 P
b10010101111111111111111111110 #
b10010101111111111111111111110 9
b10010101111111111111111111110 ?
b10010101111111111111111111110 R
b11000 4
b11000 Y
b11000 !
b11000 2
b11000 7
b11000 X
b10100 %
b10100 1
b10100 5
b10100 S
b10100 Z
b101 -
b11001010001010000110000000000001 +
1)
#24000
0)
#26000
b1000000000000000000000000000100 "
b1000000000000000000000000000100 8
b1000000000000000000000000000100 Q
b1000000000000000000000000000100 T
b100000 3
b100000 W
b100000 6
b11000 %
b11000 1
b11000 5
b11000 S
b11000 Z
b11100 4
b11100 Y
b11100 !
b11100 2
b11100 7
b11100 X
b1011000011110000111100000110 #
b1011000011110000111100000110 9
b1011000011110000111100000110 ?
b1011000011110000111100000110 R
b0 '
b0 >
b0 M
b0 P
b1100000 &
b1100000 =
b1100000 N
b1100000 U
b111000 $
b111000 <
b111000 V
b10111 -
b0 ,
b10010101111111111111111111110 +
1)
#28000
0)
#30000
b100100 3
b100100 W
b100100 6
b10000001110000000000000000001111 "
b10000001110000000000000000001111 8
b10000001110000000000000000001111 Q
b10000001110000000000000000001111 T
b1100000 $
b1100000 <
b1100000 V
b0 &
b0 =
b0 N
b0 U
b1000000000000000000000000000100 #
b1000000000000000000000000000100 9
b1000000000000000000000000000100 ?
b1000000000000000000000000000100 R
b100000 4
b100000 Y
b100000 !
b100000 2
b100000 7
b100000 X
b11100 %
b11100 1
b11100 5
b11100 S
b11100 Z
b100001 -
b1011000011110000111100000110 +
1)
#32000
0)
#34000
b10001010000000000000000000000000 "
b10001010000000000000000000000000 8
b10001010000000000000000000000000 Q
b10001010000000000000000000000000 T
b101000 3
b101000 W
b101000 6
b100000 %
b100000 1
b100000 5
b100000 S
b100000 Z
b100100 4
b100100 Y
b100100 !
b100100 2
b100100 7
b100100 X
b10000001110000000000000000001111 #
b10000001110000000000000000001111 9
b10000001110000000000000000001111 ?
b10000001110000000000000000001111 R
b0 $
b0 <
b0 V
b0 -
b1 ,
b1000000000000000000000000000100 +
1)
#36000
0)
#38000
b101100 3
b101100 W
b101100 6
b10000110101000001110000000000001 "
b10000110101000001110000000000001 8
b10000110101000001110000000000001 Q
b10000110101000001110000000000001 T
b10001010000000000000000000000000 #
b10001010000000000000000000000000 9
b10001010000000000000000000000000 ?
b10001010000000000000000000000000 R
b101000 4
b101000 Y
b101000 !
b101000 2
b101000 7
b101000 X
b100100 %
b100100 1
b100100 5
b100100 S
b100100 Z
b111000 -
b10 ,
b10000001110000000000000000001111 +
1)
#40000
0)
#42000
b100000000000000 :
b100000000000000 L
b100000000000000 O
b11000100000010000000000000000001 "
b11000100000010000000000000000001 8
b11000100000010000000000000000001 Q
b11000100000010000000000000000001 T
b110000 3
b110000 W
b110000 6
b100000000000000 ;
b100000000000000 I
b100000000000000 K
b10 @
b101000 %
b101000 1
b101000 5
b101000 S
b101000 Z
b101100 4
b101100 Y
b101100 !
b101100 2
b101100 7
b101100 X
b10000110101000001110000000000001 #
b10000110101000001110000000000001 9
b10000110101000001110000000000001 ?
b10000110101000001110000000000001 R
b0 -
b10001010000000000000000000000000 +
1)
#43000
b0 :
b0 L
b0 O
1(
#44000
0)
#46000
1F
1B
1C
b111000 ;
b111000 I
b111000 K
b0 @
b110100 3
b110100 W
b110100 6
b0 "
b0 8
b0 Q
b0 T
b11000100000010000000000000000001 #
b11000100000010000000000000000001 9
b11000100000010000000000000000001 ?
b11000100000010000000000000000001 R
b110000 4
b110000 Y
b110000 !
b110000 2
b110000 7
b110000 X
b101100 %
b101100 1
b101100 5
b101100 S
b101100 Z
b10100 -
b10000110101000001110000000000001 +
1)
#48000
0)
#50000
b10010101111111111111111111110 "
b10010101111111111111111111110 8
b10010101111111111111111111110 Q
b10010101111111111111111111110 T
b111000 3
b111000 W
b111000 6
b0 ;
b0 I
b0 K
0F
0B
0C
b110000 %
b110000 1
b110000 5
b110000 S
b110000 Z
b110100 4
b110100 Y
b110100 !
b110100 2
b110100 7
b110100 X
b0 #
b0 9
b0 ?
b0 R
b1 -
b11 ,
b11000100000010000000000000000001 +
1)
#52000
0)
#54000
b111100 3
b111100 W
b111100 6
bx "
bx 8
bx Q
bx T
b10010101111111111111111111110 #
b10010101111111111111111111110 9
b10010101111111111111111111110 ?
b10010101111111111111111111110 R
b111000 4
b111000 Y
b111000 !
b111000 2
b111000 7
b111000 X
b110100 %
b110100 1
b110100 5
b110100 S
b110100 Z
b0 -
b0 ,
b0 +
1)
#56000
0)
#58000
b1000000 3
b1000000 W
b1000000 6
b111000 %
b111000 1
b111000 5
b111000 S
b111000 Z
b111100 4
b111100 Y
b111100 !
b111100 2
b111100 7
b111100 X
bx #
bx 9
bx ?
bx R
b10111 -
b10010101111111111111111111110 +
1)
#60000
0)
#62000
b1000100 3
b1000100 W
b1000100 6
b1000000 4
b1000000 Y
b1000000 !
b1000000 2
b1000000 7
b1000000 X
b111100 %
b111100 1
b111100 5
b111100 S
b111100 Z
bx -
b0xx ,
bx +
1)
#64000
0)
#66000
b1001000 3
b1001000 W
b1001000 6
b1000000 %
b1000000 1
b1000000 5
b1000000 S
b1000000 Z
b1000100 4
b1000100 Y
b1000100 !
b1000100 2
b1000100 7
b1000100 X
1)
#68000
0)
#70000
b1001100 3
b1001100 W
b1001100 6
b1001000 4
b1001000 Y
b1001000 !
b1001000 2
b1001000 7
b1001000 X
b1000100 %
b1000100 1
b1000100 5
b1000100 S
b1000100 Z
1)
#72000
0)
#74000
b1010000 3
b1010000 W
b1010000 6
b1001000 %
b1001000 1
b1001000 5
b1001000 S
b1001000 Z
b1001100 4
b1001100 Y
b1001100 !
b1001100 2
b1001100 7
b1001100 X
1)
#76000
0)
#78000
b1010100 3
b1010100 W
b1010100 6
b1010000 4
b1010000 Y
b1010000 !
b1010000 2
b1010000 7
b1010000 X
b1001100 %
b1001100 1
b1001100 5
b1001100 S
b1001100 Z
1)
#80000
0)
#82000
b1011000 3
b1011000 W
b1011000 6
b1010000 %
b1010000 1
b1010000 5
b1010000 S
b1010000 Z
b1010100 4
b1010100 Y
b1010100 !
b1010100 2
b1010100 7
b1010100 X
1)
#84000
0)
#86000
b1011100 3
b1011100 W
b1011100 6
b1011000 4
b1011000 Y
b1011000 !
b1011000 2
b1011000 7
b1011000 X
b1010100 %
b1010100 1
b1010100 5
b1010100 S
b1010100 Z
1)
#88000
0)
