fase_2/src/MEM_WB_reg.v
// =======================================
// MEM/WB: registro de señales de control de WB
// - Aquí sólo uso 1 bit (por ejemplo RF_write_enable).
//   Si tienes más, pon [N-1:0].
// =======================================
module MEM_WB_reg (input clk, input reset, input wb_ctrl_in, output reg  wb_ctrl_out);
    always @(posedge clk) begin
        if (reset)
            wb_ctrl_out <= 1'b0; // en reset, NOP
        else
            wb_ctrl_out <= wb_ctrl_in;
    end
endmodule

fase_2/src/EX_MEM_reg.v
// =======================================
// EX/MEM: registro de señales de control de MEM
// - Ajusta [1:0] si tu bus MEM_ctrl tiene otro ancho
// =======================================
module EX_MEM_reg (input clk, input reset, input [1:0] mem_ctrl_in, output reg [1:0] mem_ctrl_out);
    always @(posedge clk) begin
        if (reset)
            mem_ctrl_out <= 2'b00; // en reset, NOP
        else
            mem_ctrl_out <= mem_ctrl_in;
    end
endmodule

fase_2/src/ID_EX_reg.v
// =======================================
// ID/EX: registro de señales de control de EX
// - Ajusta [3:0] si tu bus EX_ctrl tiene otro ancho
// =======================================
module ID_EX_reg (input clk, input reset, input [3:0] ex_ctrl_in, output reg [3:0] ex_ctrl_out);
    always @(posedge clk) begin
        if (reset)
            ex_ctrl_out <= 4'b0000; // en reset, NOP (sin control)
        else
            ex_ctrl_out <= ex_ctrl_in;
    end
endmodule

fase_2/src/CU_Mux_Control.v
////////////////////////////////////////////////////////////////////////////////////////////////////////////////////////MUX
// =======================================
// Mux de control para la Unidad de Control
// - Si S = 0: pasan las señales originales de la CU
// - Si S = 1: se inyecta un NOP (todo ceros)
// =======================================

module CU_Mux_Control (input S,
    // Entradas desde el Control Unit (en etapa ID)
    input [3:0] ex_ctrl_in,
    input [1:0] mem_ctrl_in,
    input wb_ctrl_in,
    // Salidas hacia los registros de pipeline 
    output [3:0] ex_ctrl_out,
    output [1:0] mem_ctrl_out,
    output wb_ctrl_out
);
    // logica del mux
    assign ex_ctrl_out  = (S) ? 4'b0000 : ex_ctrl_in;
    assign mem_ctrl_out = (S) ? 2'b00   : mem_ctrl_in;
    assign wb_ctrl_out  = (S) ? 1'b0    : wb_ctrl_in;
endmodule

fase_2/src/control_unit.v
`timescale 1ns / 1ps

module control_unit(
    input  [31:0] I,
    output reg [3:0] ALU_OP,
    output reg [1:0] RAM_Size,
    output reg       RAM_RW,
    output reg       RAM_Enable,
    output reg       L,
    output reg       RF_LE
);

    // Combinational control logic
    always @(*) begin
        // Default values
        ALU_OP     = 4'b0000;
        RAM_Size   = 2'b00;
        RAM_RW     = 1'b0;
        RAM_Enable = 1'b0;
        L          = 1'b0;
        RF_LE      = 1'b0;

        case (I[31:30])
            2'b01: begin
                // Format 1: CALL (placeholder)
                // You can add behavior here if needed.
            end

            2'b00: begin // Format 2
                case (I[24:22]) // op2 field
                    3'b010: begin // BRANCH
                        // Placeholder for branch control
                    end
                    3'b100: begin // SETHI
                        // Example operation: this would normally load an immediate
                        // No rd_data signal declared here, so we skip that assignment
                    end
                endcase
            end

            2'b10: begin // Format 3: Arithmetic/Logic
                case (I[24:19]) // op3
                    // Arithmetic
                    6'b010000: ALU_OP = 4'b0000; // addcc
                    6'b011000: ALU_OP = 4'b0001; // addxcc
                    6'b010100: ALU_OP = 4'b0010; // subcc
                    6'b011100: ALU_OP = 4'b0011; // subxcc

                    // Logical
                    6'b010001: ALU_OP = 4'b0100; // andcc
                    6'b010010: ALU_OP = 4'b0101; // orcc
                    6'b010011: ALU_OP = 4'b0110; // xorcc
                    6'b010111: ALU_OP = 4'b0111; // xnorcc
                    6'b010101: ALU_OP = 4'b1000; // andncc
                    6'b010110: ALU_OP = 4'b1001; // orncc

                    // Shifts
                    6'b100101: ALU_OP = 4'b1010; // sll
                    6'b100110: ALU_OP = 4'b1011; // srl
                    6'b100111: ALU_OP = 4'b1100; // sra
                endcase
            end

            2'b11: begin // Format 3: Load/Store
                case (I[24:19]) // op3
                    // Loads
                    6'b001001: begin // lsb
                        RAM_Size = 2'b00;
                        RAM_RW   = 1'b0;
                        RAM_Enable = 1'b1;
                        L        = 1'b1;
                        RF_LE    = 1'b1;
                    end
                    6'b001010: begin // ldsh
                        RAM_Size = 2'b01;
                        RAM_RW   = 1'b0;
                        RAM_Enable = 1'b1;
                        L        = 1'b1;
                        RF_LE    = 1'b1;
                    end
                    6'b000000: begin // ld
                        RAM_Size = 2'b10;
                        RAM_RW   = 1'b0;
                        RAM_Enable = 1'b1;
                        L        = 1'b1;
                        RF_LE    = 1'b1;
                    end
                    6'b000001: begin // ldub
                        RAM_Size = 2'b00;
                        RAM_RW   = 1'b0;
                        RAM_Enable = 1'b1;
                        L        = 1'b1;
                        RF_LE    = 1'b1;
                    end
                    6'b000010: begin // lduh
                        RAM_Size = 2'b01;
                        RAM_RW   = 1'b0;
                        RAM_Enable = 1'b1;
                        L        = 1'b1;
                        RF_LE    = 1'b1;
                    end
                    6'b000011: begin // ldd
                        RAM_Size = 2'b11;
                        RAM_RW   = 1'b0;
                        RAM_Enable = 1'b1;
                        L        = 1'b1;
                        RF_LE    = 1'b1;
                    end

                    // Stores
                    6'b000101: begin // stb
                        RAM_Size   = 2'b00;
                        RAM_RW     = 1'b1;
                        RAM_Enable = 1'b1;
                    end
                    6'b000110: begin // sth
                        RAM_Size   = 2'b01;
                        RAM_RW     = 1'b1;
                        RAM_Enable = 1'b1;
                    end
                    6'b000100: begin // st
                        RAM_Size   = 2'b10;
                        RAM_RW     = 1'b1;
                        RAM_Enable = 1'b1;
                    end
                    6'b000111: begin // std
                        RAM_Size   = 2'b11;
                        RAM_RW     = 1'b1;
                        RAM_Enable = 1'b1;
                    end
                    6'b001101: begin // ldstub
                        RAM_Size   = 2'b00;
                        RAM_RW     = 1'b1;
                        RAM_Enable = 1'b1;
                    end
                    6'b001111: begin // swap
                        RAM_Size   = 2'b10;
                        RAM_RW     = 1'b1;
                        RAM_Enable = 1'b1;
                    end
                endcase
            end

            default: begin
                // no-op
            end
        endcase
    end

endmodule

fase_2/src/IF_IF_reg.v
//////////////////////////////////////////////////////////////////////////////////////////////////////////////Pipeline Reg
//Registros Pipeline

// =======================================
// IF/ID: registro de instrucción
// - Rising edge-triggered
// - Reset sincrónico
// - Sin load enable (siempre carga)
// =======================================
module IF_ID_reg (input clk, input reset, input [31:0] instr_in, output reg [31:0] instr_out);
    always @(posedge clk) begin
        if (reset)
            instr_out <= 32'd0;    // en reset, NOP (instrucción = 0)
        else
            instr_out <= instr_in; // siempre carga en cada ciclo
    end
endmodule

fase_2/src/instruction_memory.v
module instruction_memory (
    input [8:0] A,
    output reg [31:0] I
);
    reg [7:0] Memory [0:511];

    always @(*) begin
        I = {Memory[A], Memory[A+1], Memory[A+2], Memory[A+3]};
        if (A > 508) I = 32'b0;
    end

    initial begin
        $readmemb("precharge.txt", Memory);
    end
endmodule

fase_2/src/NPC_reg.v
module NPC_reg (
    input clk,
    input reset,
    input LE,
    input [31:0] D,
    output reg [31:0] Q
);
    always @(posedge clk) begin
        if (reset)
            Q <= 32'd4;
        else if (LE)
            Q <= D;
    end
endmodule

fase_2/src/PC_reg.v
module PC_reg (
    input clk,
    input reset,
    input LE,
    input [31:0] D,
    output reg [31:0] Q
);
    always @(posedge clk) begin
        if (reset)
            Q <= 32'd0;
        else if (LE)
            Q <= D;
    end
endmodule

fase_2/src/PPU_ControlPath.v
/////////////////////////////////////////////////////////////////////////////////////////Control path
// TOP: PPU_ControlPath
// - Conecta PC, nPC, Instruction Memory, IF/ID, Control Unit,
//   MUX de control y pipeline de señales EX/MEM/WB.

module PPU_ControlPath (
    input        clk,
    input        reset,
    input        S,               // selección del MUX de control

    // Salidas para debugging / testbench
    output [31:0] PC,
    output [31:0] nPC,
    output [31:0] instr_IF,
    output [31:0] instr_ID,
    output [3:0]  EX_ctrl,
    output [1:0]  MEM_ctrl,
    output        WB_ctrl
);

    // ---------------- PC y nPC ----------------
    wire [31:0] pc_actual, npc_actual;
    wire [31:0] pc_next, npc_next, npc_plus_4;

    assign PC  = pc_actual;
    assign nPC = npc_actual;

    // nPC_next = nPC_actual + 4; PC_next = nPC_actual
    assign npc_plus_4 = npc_actual + 32'd4;
    assign pc_next    = npc_actual;
    assign npc_next   = npc_plus_4;

    // Load enable (siempre 1 por ahora)
    wire LE_PC  = 1'b1;
    wire LE_nPC = 1'b1;

    // Instancia de PC
    PC_reg PC0 (
        .clk   (clk),
        .reset (reset),
        .LE    (LE_PC),
        .D     (pc_next),
        .Q     (pc_actual)
    );

    // Instancia de nPC
    NPC_reg NPC0 (
        .clk   (clk),
        .reset (reset),
        .LE    (LE_nPC),
        .D     (npc_next),
        .Q     (npc_actual)
    );

    // ---------------- Instruction Memory ----------------
    instruction_memory IMEM (
        .A(pc_actual[8:0]),   // dirección en bytes: PC[8:0]
        .I(instr_IF)
    );

    // ---------------- IF/ID: instrucción hacia la CU ----------------
    IF_ID_reg IF_ID (
        .clk      (clk),
        .reset    (reset),
        .instr_in (instr_IF),
        .instr_out(instr_ID)
    );

    // ---------------- Control Unit (en etapa ID) ----------------
    wire [3:0] ALU_OP;
    wire [1:0] RAM_Size;
    wire       RAM_RW, RAM_Enable, L, RF_LE;

    control_unit CU (
        .I         (instr_ID),
        .ALU_OP    (ALU_OP),
        .RAM_Size  (RAM_Size),
        .RAM_RW    (RAM_RW),
        .RAM_Enable(RAM_Enable),
        .L         (L),
        .RF_LE     (RF_LE)
    );

    // Para esta fase, mapeamos:
    //  - EX_ctrl_id  = ALU_OP (4 bits)
    //  - MEM_ctrl_id = RAM_Size (2 bits)
    //  - WB_ctrl_id  = RF_LE (1 bit)
    wire [3:0] ex_ctrl_id  = ALU_OP;
    wire [1:0] mem_ctrl_id = RAM_Size;
    wire       wb_ctrl_id  = RF_LE;

    // ---------------- Mux de control de la CU ----------------
    wire [3:0] ex_ctrl_mux;
    wire [1:0] mem_ctrl_mux;
    wire       wb_ctrl_mux;

    CU_Mux_Control CU_MUX (
        .S           (S),
        .ex_ctrl_in  (ex_ctrl_id),
        .mem_ctrl_in (mem_ctrl_id),
        .wb_ctrl_in  (wb_ctrl_id),
        .ex_ctrl_out (ex_ctrl_mux),
        .mem_ctrl_out(mem_ctrl_mux),
        .wb_ctrl_out (wb_ctrl_mux)
    );

    // ---------------- Registros de pipeline de control ----------------
    // ID/EX
    ID_EX_reg ID_EX (
        .clk        (clk),
        .reset      (reset),
        .ex_ctrl_in (ex_ctrl_mux),
        .ex_ctrl_out(EX_ctrl)
    );

    // EX/MEM
    EX_MEM_reg EX_MEM (
        .clk         (clk),
        .reset       (reset),
        .mem_ctrl_in (mem_ctrl_mux),
        .mem_ctrl_out(MEM_ctrl)
    );

    // MEM/WB
    MEM_WB_reg MEM_WB (
        .clk        (clk),
        .reset      (reset),
        .wb_ctrl_in (wb_ctrl_mux),
        .wb_ctrl_out(WB_ctrl)
    );

endmodule

fase_2/src/PPU_ControlPath_tb.v
`timescale 1ns / 1ps

module PPU_ControlPath_tb;

    // Testbench signals
    reg clk;
    reg reset;
    reg S;
    wire [31:0] PC, nPC, instr_IF, instr_ID;
    wire [3:0]  EX_ctrl;
    wire [1:0]  MEM_ctrl;
    wire        WB_ctrl;

    // Instantiate the DUT (Device Under Test)
    PPU_ControlPath dut (
        .clk(clk),
        .reset(reset),
        .S(S),
        .PC(PC),
        .nPC(nPC),
        .instr_IF(instr_IF),
        .instr_ID(instr_ID),
        .EX_ctrl(EX_ctrl),
        .MEM_ctrl(MEM_ctrl),
        .WB_ctrl(WB_ctrl)
    );

    // Clock generator: toggles every 2ns → period = 4ns
    initial begin
        clk = 0;
        forever #2 clk = ~clk;
    end

    // Test sequence according to spec
    initial begin
        $dumpfile("PPU_ControlPath_tb.vcd");
        $dumpvars(0, PPU_ControlPath_tb);

        // Inicialización
        reset = 1;
        S = 0;

        // Reset va a 0 en t=3 ns
        #3 reset = 0;

        // S cambia a 1 en t=40 ns
        #37 S = 1;

        // Finaliza en t=48 ns
        #8;
        $display("=== SIMULACIÓN FINALIZADA ===");
        $finish;
    end

    // --- Instrucción decodificada (opcional) ---
    reg [7:0] opcode;
    reg [5:0]  opcode3;
    reg [31:0] instr_word;

    // Cada flanco positivo del reloj, imprimir estado
    always @(posedge clk) begin
        instr_word = instr_ID;
        opcode = instr_word[31:30];
        opcode3 = instr_word[24:19];
        $display("------------------------------------------------");
        $write("t=%0t ns | ", $time);
        case (opcode)
            2'b00: $write("Instr=SETHI or BRANCH ");   // Format 2
            2'b01: $write("Instr=CALL ");              // Format 1

            2'b10: begin // Format 3 – Arithmetic, Logic, Shift, Save/Restore, Trap, etc.
                case (opcode3)
                    // Basic Arithmetic Instructions
                    6'b000000: $write("Instr=ADD ");
                    6'b010000: $write("Instr=ADDCC ");
                    6'b001000: $write("Instr=ADDX ");
                    6'b011000: $write("Instr=ADDXCC ");
                    6'b000100: $write("Instr=SUB ");
                    6'b010100: $write("Instr=SUBCC ");
                    6'b001100: $write("Instr=SUBX ");
                    6'b011100: $write("Instr=SUBXCC ");
                    // Tagged Arithmetic Instructions
                    6'b100000: $write("Instr=TADDCC ");
                    6'b100010: $write("Instr=TADDCCTV ");
                    6'b100001: $write("Instr=TSUBCC ");
                    6'b100011: $write("Instr=TSUBCCTV ");
                    // Other Arithmetic Instructions
                    6'b100101: $write("Instr=MULSCC ");
                    6'b001010: $write("Instr=UMUL ");
                    6'b011010: $write("Instr=UMULCC ");
                    6'b001001: $write("Instr=SMUL ");
                    6'b011001: $write("Instr=SMULCC ");
                    6'b001110: $write("Instr=UDIV ");
                    6'b011110: $write("Instr=UDIVCC ");
                    6'b001111: $write("Instr=SDIV ");
                    6'b011111: $write("Instr=SDIVCC ");

                    // Logical Instructions
                    6'b000001: $write("Instr=AND ");
                    6'b010001: $write("Instr=ANDCC ");
                    6'b000101: $write("Instr=ANDN ");
                    6'b010101: $write("Instr=ANDNCC ");
                    6'b000010: $write("Instr=OR ");
                    6'b010010: $write("Instr=ORCC ");
                    6'b000110: $write("Instr=ORN ");
                    6'b010110: $write("Instr=ORNCC ");
                    6'b000011: $write("Instr=XOR ");
                    6'b010011: $write("Instr=XORCC ");
                    6'b000111: $write("Instr=XNOR ");
                    6'b010111: $write("Instr=XNORCC ");

                    // Shift Instructions
                    6'b100101: $write("Instr=SLL ");
                    6'b100110: $write("Instr=SRL ");
                    6'b100111: $write("Instr=SRA ");

                    // Save and Restore Instruction Format
                    6'b111100: $write("Instr=SAVE ");
                    6'b111101: $write("Instr=RESTORE ");

                    // jumpl Instruction
                    6'b111000: $write("Instr=JMPL ");

                    // Trap on Integer Condition Codes
                    6'b111010: $write("Instr=TRAP "); // These expand even more, slide 54 of CA SPARC Architecture
                    
                    // Return from Trap Instruction - RETT
                    6'b111001: $write("Instr=RETT ");

                    // Read State Register Instructions
                    6'b101001: $write("Instr=RDPSR ");
                    6'b101010: $write("Instr=RDWIM ");
                    6'b101011: $write("Instr=RDTBR ");

                    // Write State Register Instructions
                    6'b110001: $write("Instr=WRPSR ");
                    6'b110010: $write("Instr=WRWIM ");
                    6'b110011: $write("Instr=WRTBR ");

                    default:   $write("Instr=UNKNOWN (op3=%b)", opcode3);
                endcase
            end

            2'b11: begin
                case (opcode3)
                    6'b001001: $write("Instr=LSB ");
                    6'b001010: $write("Instr=LDSH ");
                    6'b000000: $write("Instr=LD ");
                    6'b000001: $write("Instr=LDUB ");
                    6'b000010: $write("Instr=LDUH ");
                    6'b000011: $write("Instr=LDD ");
                    6'b000101: $write("Instr=STB ");
                    6'b000110: $write("Instr=STH ");
                    6'b000100: $write("Instr=ST ");
                    6'b000111: $write("Instr=STD ");
                    6'b001101: $write("Instr=LDSTUB ");
                    6'b001111: $write("Instr=SWAP ");
                    default:   $write("Instr=LOAD/STORE OTHER ");
                endcase
            end

            default: $write("Instr=UNKNOWN OP ");
        endcase

        $display("| PC=%0d | nPC=%0d", PC, nPC);
        $display("EX_ctrl=%b", EX_ctrl);
        $display("MEM_ctrl=%b", MEM_ctrl);
        $display("WB_ctrl=%b", WB_ctrl);
    end

endmodule

fase_2/src/PPU_ControlPath_tb.vcd
$date
	Sat Nov 08 15:13:44 2025
$end
$version
	Icarus Verilog
$end
$timescale
	1ps
$end
$scope module PPU_ControlPath_tb $end
$var wire 32 ! nPC [31:0] $end
$var wire 32 " instr_IF [31:0] $end
$var wire 32 # instr_ID [31:0] $end
$var wire 1 $ WB_ctrl $end
$var wire 32 % PC [31:0] $end
$var wire 2 & MEM_ctrl [1:0] $end
$var wire 4 ' EX_ctrl [3:0] $end
$var reg 1 ( S $end
$var reg 1 ) clk $end
$var reg 32 * instr_word [31:0] $end
$var reg 8 + opcode [7:0] $end
$var reg 6 , opcode3 [5:0] $end
$var reg 1 - reset $end
$scope module dut $end
$var wire 1 . LE_PC $end
$var wire 1 / LE_nPC $end
$var wire 32 0 PC [31:0] $end
$var wire 1 ( S $end
$var wire 1 ) clk $end
$var wire 4 1 ex_ctrl_id [3:0] $end
$var wire 2 2 mem_ctrl_id [1:0] $end
$var wire 32 3 nPC [31:0] $end
$var wire 32 4 npc_next [31:0] $end
$var wire 32 5 pc_next [31:0] $end
$var wire 1 - reset $end
$var wire 1 6 wb_ctrl_id $end
$var wire 1 7 wb_ctrl_mux $end
$var wire 32 8 pc_actual [31:0] $end
$var wire 32 9 npc_plus_4 [31:0] $end
$var wire 32 : npc_actual [31:0] $end
$var wire 2 ; mem_ctrl_mux [1:0] $end
$var wire 32 < instr_IF [31:0] $end
$var wire 32 = instr_ID [31:0] $end
$var wire 4 > ex_ctrl_mux [3:0] $end
$var wire 1 $ WB_ctrl $end
$var wire 1 ? RF_LE $end
$var wire 2 @ RAM_Size [1:0] $end
$var wire 1 A RAM_RW $end
$var wire 1 B RAM_Enable $end
$var wire 2 C MEM_ctrl [1:0] $end
$var wire 1 D L $end
$var wire 4 E EX_ctrl [3:0] $end
$var wire 4 F ALU_OP [3:0] $end
$scope module CU $end
$var wire 32 G I [31:0] $end
$var reg 4 H ALU_OP [3:0] $end
$var reg 1 D L $end
$var reg 1 B RAM_Enable $end
$var reg 1 A RAM_RW $end
$var reg 2 I RAM_Size [1:0] $end
$var reg 1 ? RF_LE $end
$upscope $end
$scope module CU_MUX $end
$var wire 1 ( S $end
$var wire 4 J ex_ctrl_in [3:0] $end
$var wire 2 K mem_ctrl_in [1:0] $end
$var wire 1 6 wb_ctrl_in $end
$var wire 1 7 wb_ctrl_out $end
$var wire 2 L mem_ctrl_out [1:0] $end
$var wire 4 M ex_ctrl_out [3:0] $end
$upscope $end
$scope module EX_MEM $end
$var wire 1 ) clk $end
$var wire 2 N mem_ctrl_in [1:0] $end
$var wire 1 - reset $end
$var reg 2 O mem_ctrl_out [1:0] $end
$upscope $end
$scope module ID_EX $end
$var wire 1 ) clk $end
$var wire 4 P ex_ctrl_in [3:0] $end
$var wire 1 - reset $end
$var reg 4 Q ex_ctrl_out [3:0] $end
$upscope $end
$scope module IF_ID $end
$var wire 1 ) clk $end
$var wire 1 - reset $end
$var wire 32 R instr_in [31:0] $end
$var reg 32 S instr_out [31:0] $end
$upscope $end
$scope module IMEM $end
$var wire 9 T A [8:0] $end
$var reg 32 U I [31:0] $end
$upscope $end
$scope module MEM_WB $end
$var wire 1 ) clk $end
$var wire 1 - reset $end
$var wire 1 7 wb_ctrl_in $end
$var reg 1 $ wb_ctrl_out $end
$upscope $end
$scope module NPC0 $end
$var wire 32 V D [31:0] $end
$var wire 1 / LE $end
$var wire 1 ) clk $end
$var wire 1 - reset $end
$var reg 32 W Q [31:0] $end
$upscope $end
$scope module PC0 $end
$var wire 32 X D [31:0] $end
$var wire 1 . LE $end
$var wire 1 ) clk $end
$var wire 1 - reset $end
$var reg 32 Y Q [31:0] $end
$upscope $end
$upscope $end
$upscope $end
$enddefinitions $end
$comment Show the parameter values. $end
$dumpall
$end
#0
$dumpvars
bx Y
bx X
bx W
bx V
bx U
bx T
bx S
bx R
bx Q
bx P
bx O
bx N
bx M
bx L
bx K
bx J
bx I
bx H
bx G
bx F
bx E
xD
bx C
xB
xA
bx @
x?
bx >
bx =
bx <
bx ;
bx :
bx 9
bx 8
x7
x6
bx 5
bx 4
bx 3
bx 2
bx 1
bx 0
1/
1.
1-
bx ,
bx +
bx *
0)
0(
bx '
bx &
bx %
x$
bx #
bx "
bx !
$end
#2000
b10001010000000000000000000000000 "
b10001010000000000000000000000000 <
b10001010000000000000000000000000 R
b10001010000000000000000000000000 U
07
b0 ;
b0 L
b0 N
b0 >
b0 M
b0 P
b0 T
06
0?
0D
0B
0A
b0 2
b0 K
b0 @
b0 I
b0 1
b0 J
b0 F
b0 H
b0 %
b0 0
b0 8
b0 Y
b1000 4
b1000 V
b1000 9
b100 5
b100 X
b100 !
b100 3
b100 :
b100 W
b0 #
b0 =
b0 G
b0 S
b0 '
b0 E
b0 Q
b0 &
b0 C
b0 O
0$
b0xx +
1)
#3000
0-
#4000
0)
#6000
b10000110101000001110000000000001 "
b10000110101000001110000000000001 <
b10000110101000001110000000000001 R
b10000110101000001110000000000001 U
b100 T
b10001010000000000000000000000000 #
b10001010000000000000000000000000 =
b10001010000000000000000000000000 G
b10001010000000000000000000000000 S
b1100 4
b1100 V
b1100 9
b1000 5
b1000 X
b1000 !
b1000 3
b1000 :
b1000 W
b100 %
b100 0
b100 8
b100 Y
b0 ,
b0 +
b0 *
1)
#8000
0)
#10000
b11000100000010000000000000000001 "
b11000100000010000000000000000001 <
b11000100000010000000000000000001 R
b11000100000010000000000000000001 U
b10 >
b10 M
b10 P
b1000 T
b10 1
b10 J
b10 F
b10 H
b1000 %
b1000 0
b1000 8
b1000 Y
b10000 4
b10000 V
b10000 9
b1100 5
b1100 X
b1100 !
b1100 3
b1100 :
b1100 W
b10000110101000001110000000000001 #
b10000110101000001110000000000001 =
b10000110101000001110000000000001 G
b10000110101000001110000000000001 S
b10 +
b10001010000000000000000000000000 *
1)
#12000
0)
#14000
17
b0 >
b0 M
b0 P
b11001010001010000110000000000001 "
b11001010001010000110000000000001 <
b11001010001010000110000000000001 R
b11001010001010000110000000000001 U
16
1?
1D
1B
b0 1
b0 J
b0 F
b0 H
b1100 T
b10 '
b10 E
b10 Q
b11000100000010000000000000000001 #
b11000100000010000000000000000001 =
b11000100000010000000000000000001 G
b11000100000010000000000000000001 S
b10100 4
b10100 V
b10100 9
b10000 5
b10000 X
b10000 !
b10000 3
b10000 :
b10000 W
b1100 %
b1100 0
b1100 8
b1100 Y
b10100 ,
b10000110101000001110000000000001 *
1)
#16000
0)
#18000
b10010101111111111111111111110 "
b10010101111111111111111111110 <
b10010101111111111111111111110 R
b10010101111111111111111111110 U
07
b10000 T
1A
06
0?
0D
1B
b10000 %
b10000 0
b10000 8
b10000 Y
b11000 4
b11000 V
b11000 9
b10100 5
b10100 X
b10100 !
b10100 3
b10100 :
b10100 W
b11001010001010000110000000000001 #
b11001010001010000110000000000001 =
b11001010001010000110000000000001 G
b11001010001010000110000000000001 S
b0 '
b0 E
b0 Q
1$
b1 ,
b11 +
b11000100000010000000000000000001 *
1)
#20000
0)
#22000
b1011000011110000111100000110 "
b1011000011110000111100000110 <
b1011000011110000111100000110 R
b1011000011110000111100000110 U
0B
0A
b10100 T
0$
b10010101111111111111111111110 #
b10010101111111111111111111110 =
b10010101111111111111111111110 G
b10010101111111111111111111110 S
b11100 4
b11100 V
b11100 9
b11000 5
b11000 X
b11000 !
b11000 3
b11000 :
b11000 W
b10100 %
b10100 0
b10100 8
b10100 Y
b101 ,
b11001010001010000110000000000001 *
1)
#24000
0)
#26000
b1000000000000000000000000000100 "
b1000000000000000000000000000100 <
b1000000000000000000000000000100 R
b1000000000000000000000000000100 U
b11000 T
b11000 %
b11000 0
b11000 8
b11000 Y
b100000 4
b100000 V
b100000 9
b11100 5
b11100 X
b11100 !
b11100 3
b11100 :
b11100 W
b1011000011110000111100000110 #
b1011000011110000111100000110 =
b1011000011110000111100000110 G
b1011000011110000111100000110 S
b10111 ,
b0 +
b10010101111111111111111111110 *
1)
#28000
0)
#30000
b10000001110000000000000000001111 "
b10000001110000000000000000001111 <
b10000001110000000000000000001111 R
b10000001110000000000000000001111 U
b11100 T
b1000000000000000000000000000100 #
b1000000000000000000000000000100 =
b1000000000000000000000000000100 G
b1000000000000000000000000000100 S
b100100 4
b100100 V
b100100 9
b100000 5
b100000 X
b100000 !
b100000 3
b100000 :
b100000 W
b11100 %
b11100 0
b11100 8
b11100 Y
b100001 ,
b1011000011110000111100000110 *
1)
#32000
0)
#34000
b10001010000000000000000000000000 "
b10001010000000000000000000000000 <
b10001010000000000000000000000000 R
b10001010000000000000000000000000 U
b100000 T
b100000 %
b100000 0
b100000 8
b100000 Y
b101000 4
b101000 V
b101000 9
b100100 5
b100100 X
b100100 !
b100100 3
b100100 :
b100100 W
b10000001110000000000000000001111 #
b10000001110000000000000000001111 =
b10000001110000000000000000001111 G
b10000001110000000000000000001111 S
b0 ,
b1 +
b1000000000000000000000000000100 *
1)
#36000
0)
#38000
b10000110101000001110000000000001 "
b10000110101000001110000000000001 <
b10000110101000001110000000000001 R
b10000110101000001110000000000001 U
b100100 T
b10001010000000000000000000000000 #
b10001010000000000000000000000000 =
b10001010000000000000000000000000 G
b10001010000000000000000000000000 S
b101100 4
b101100 V
b101100 9
b101000 5
b101000 X
b101000 !
b101000 3
b101000 :
b101000 W
b100100 %
b100100 0
b100100 8
b100100 Y
b111000 ,
b10 +
b10000001110000000000000000001111 *
1)
#40000
0)
1(
#42000
b11000100000010000000000000000001 "
b11000100000010000000000000000001 <
b11000100000010000000000000000001 R
b11000100000010000000000000000001 U
b101000 T
b10 1
b10 J
b10 F
b10 H
b101000 %
b101000 0
b101000 8
b101000 Y
b110000 4
b110000 V
b110000 9
b101100 5
b101100 X
b101100 !
b101100 3
b101100 :
b101100 W
b10000110101000001110000000000001 #
b10000110101000001110000000000001 =
b10000110101000001110000000000001 G
b10000110101000001110000000000001 S
b0 ,
b10001010000000000000000000000000 *
1)
#44000
0)
#46000
b0 "
b0 <
b0 R
b0 U
16
1?
1D
1B
b0 1
b0 J
b0 F
b0 H
b101100 T
b11000100000010000000000000000001 #
b11000100000010000000000000000001 =
b11000100000010000000000000000001 G
b11000100000010000000000000000001 S
b110100 4
b110100 V
b110100 9
b110000 5
b110000 X
b110000 !
b110000 3
b110000 :
b110000 W
b101100 %
b101100 0
b101100 8
b101100 Y
b10100 ,
b10000110101000001110000000000001 *
1)
